datecalendar.py
datecalendar-0.1.4.post0.dist-info/LICENSE
datecalendar-0.1.4.post0.dist-info/METADATA
datecalendar-0.1.4.post0.dist-info/WHEEL
datecalendar-0.1.4.post0.dist-info/top_level.txt
datecalendar-0.1.4.post0.dist-info/RECORD
