Metadata-Version: 2.1
Name: datecalendar
Version: 0.1.4.post0
Summary: Replicates the DateCalendar.sol algorithms responsible for storing each date's proof of ownership.
Home-page: https://datecalendar.io
Author: dcgub
License: MIT
Platform: UNKNOWN
Classifier: Intended Audience :: Developers
Classifier: License :: OSI Approved :: MIT License
Classifier: Development Status :: 5 - Production/Stable
Classifier: Operating System :: OS Independent
Classifier: Programming Language :: Python :: 3
Classifier: Programming Language :: Python :: 3.8
Classifier: Programming Language :: Python :: 3.9
Classifier: Natural Language :: English
Requires-Python: >=3.8
Requires-Dist: python-dateutil
